wikdict_compound/__init__.py
wikdict_compound/make_db.py
wikdict_compound-0.2.dist-info/LICENSE
wikdict_compound-0.2.dist-info/METADATA
wikdict_compound-0.2.dist-info/WHEEL
wikdict_compound-0.2.dist-info/top_level.txt
wikdict_compound-0.2.dist-info/RECORD
