Metadata-Version: 2.1
Name: wikdict-compound
Version: 0.2
Summary: Compound word splitter, dictionary-based
Home-page: https://github.com/karlb/wikdict-compound
Author: Karl Bartel
Project-URL: Issues, https://github.com/karlb/wikdict-compound/issues
Project-URL: CI, https://github.com/karlb/wikdict-compound/actions
Project-URL: Changelog, https://github.com/karlb/wikdict-compound/releases
Requires-Python: >=3.9
License-File: LICENSE
Provides-Extra: test
Requires-Dist: pytest ; extra == 'test'
